ft2bt/__init__.py
ft2bt/scripts/__init__.py
ft2bt/scripts/ft2bt.py
ft2bt/scripts/behavior_trees/__init__.py
ft2bt/scripts/behavior_trees/behavior_tree.py
ft2bt/scripts/behavior_trees/behavior_tree_node.py
ft2bt/scripts/code_generator/__init__.py
ft2bt/scripts/code_generator/code_generator.py
ft2bt/scripts/code_generator/header_file.py
ft2bt/scripts/code_generator/main_file.py
ft2bt/scripts/code_generator/source_file.py
ft2bt/scripts/fault_trees/__init__.py
ft2bt/scripts/fault_trees/xml_fta_parser.py
ft2bt/scripts/formal_verification/__init__.py
ft2bt/scripts/formal_verification/ctl_specification_generator.py
ft2bt/scripts/formal_verification/smv_header.txt
ft2bt/scripts/formal_verification/supervisor_model_generator.py
ft2bt/scripts/hara/__init__.py
ft2bt/scripts/hara/hara_parser.py
ft2bt/test/test_1.py
ft2bt/test/test_2.py
ft2bt/test/test_3.py
ft2bt/test/behavior_trees/render/BT_hz_01.svg
ft2bt/test/fault_trees/fta_example.png
ft2bt/test/fault_trees/fta_example.xml
ft2bt/test/fault_trees/fta_real.xml
ft2bt/test/hara/hara_example.csv
ft2bt/test/hara/hara_example.png
ft2bt/test/hara/hara_real.csv
ft2bt-0.7.0.dist-info/LICENSE
ft2bt-0.7.0.dist-info/METADATA
ft2bt-0.7.0.dist-info/WHEEL
ft2bt-0.7.0.dist-info/entry_points.txt
ft2bt-0.7.0.dist-info/top_level.txt
ft2bt-0.7.0.dist-info/RECORD
