Metadata-Version: 2.1
Name: ft2bt
Version: 0.7.0
Summary: Automatic conversion from fault trees into behavior trees with formal verification capabilities
Home-page: https://github.com/cconejob/ft2bt_converter.git
Author: Carlos Conejo
Author-email: carlos.conejo@upc.edu
License: GNU GPLv3
Classifier: Programming Language :: Python :: 3
Classifier: License :: OSI Approved :: GNU General Public License v3 (GPLv3)
Classifier: Operating System :: OS Independent
Requires-Python: >=3.6
License-File: LICENSE
Requires-Dist: networkx>=2.8.8
Requires-Dist: graphviz>=0.20.1
Requires-Dist: matplotlib>=3.6.2
Requires-Dist: cloudpickle>=1.3.0
Requires-Dist: future>=0.18.2
Requires-Dist: fvcore<0.1.4,>=0.1.3
Requires-Dist: iopath>=0.1.2
Requires-Dist: omegaconf>=2
Requires-Dist: pycocotools>=2.0.2
Requires-Dist: pydot>=1.4.1
Requires-Dist: tabulate>=0.8.9
Requires-Dist: tensorboard>=2.1.1
Requires-Dist: termcolor>=1.1
Requires-Dist: tqdm>4.29.0
Requires-Dist: yacs>=0.1.6
